PEUQSE/CiteSoftLocal.py
PEUQSE/CombinationGeneratorModule.py
PEUQSE/InverseProblem.py
PEUQSE/LICENSE.txt
PEUQSE/MANUAL.txt
PEUQSE/UserInput.py
PEUQSE/__init__.py
PEUQSE/mumpce_custom_plotting_example.py
PEUQSE/nestedObjectsFunctionsLocal.py
PEUQSE/parallel_processing.py
PEUQSE/plotting_functions.py
PEUQSE/test_pytest.py
PEUQSE/mumpce/Project.py
PEUQSE/mumpce/__init__.py
PEUQSE/mumpce/measurement.py
PEUQSE/mumpce/model.py
PEUQSE/mumpce/response_surface.py
PEUQSE/mumpce/solution.py
PEUQSE/simulationDriver/__init__.py
PEUQSE/simulationDriver/canteraKineticsParametersParser.py
PEUQSE/simulationDriver/canteraSimulate.py
PEUQSE/simulationDriver/ceO2_input_simulation_settings.py
PEUQSE/simulationDriver/example_modifyAllAdjustableReactionParametersArrayValues.py
PEUQSE/simulationDriver/example_runfile.py
PEUQSE/simulationDriver/scratch.py
PEUQSE/simulationDriver_CTI/__init__.py
PEUQSE/simulationDriver_CTI/canteraKineticsParametersParser.py
PEUQSE/simulationDriver_CTI/canteraSimulate.py
PEUQSE/simulationDriver_CTI/ceO2_input_simulation_settings.py
PEUQSE/simulationDriver_CTI/example_modifyAllAdjustableReactionParametersArrayValues.py
PEUQSE/simulationDriver_CTI/example_runfile.py
peuqse-1.3.0.data/data/LICENSE.txt
peuqse-1.3.0.data/data/MANUAL.txt
peuqse-1.3.0.dist-info/METADATA
peuqse-1.3.0.dist-info/WHEEL
peuqse-1.3.0.dist-info/top_level.txt
peuqse-1.3.0.dist-info/RECORD
