Metadata-Version: 2.1
Name: peuqse
Version: 1.3.0
Summary: This is the PEUQSE package which stands for Parameter Estimation and Uncertainty Quantification for Science and Engineering. See https://github.com/AdityaSavara/PEUQSE for more information.
Home-page: https://github.com/AdityaSavara/PEUQSE
Author: Aditya Savara
Author-email: AditySavara2008@u.northwestern.edu
License: BSD-3-Clause
Classifier: License :: OSI Approved :: BSD License
Classifier: Programming Language :: Python
Classifier: Programming Language :: Python :: 3
Classifier: Programming Language :: Python :: 3.6
Classifier: Programming Language :: Python :: Implementation :: CPython
Classifier: Programming Language :: Python :: Implementation :: PyPy
Requires-Python: >=3.5.0
Requires-Dist: numpy
Requires-Dist: dill
Requires-Dist: pandas
Requires-Dist: matplotlib
Requires-Dist: scipy
Provides-Extra: complete
Requires-Dist: UnitTesterSG>=6.2.2; extra == "complete"
Requires-Dist: matplotlib; extra == "complete"
Requires-Dist: scipy; extra == "complete"
Requires-Dist: numpy; extra == "complete"
Requires-Dist: pandas; extra == "complete"
Requires-Dist: CiteSoft; extra == "complete"
Requires-Dist: zeus-mcmc>=2.4.0; extra == "complete"
Requires-Dist: dill; extra == "complete"
Requires-Dist: emcee; extra == "complete"
